ivy_demo_utils/__init__.py
ivy_demo_utils/framework_utils.py
ivy_demo_utils/open3d_utils.py
ivy_demo_utils/ivy_scene/__init__.py
ivy_demo_utils/ivy_scene/scene.ttt
ivy_demo_utils/ivy_scene/scene_utils.py
ivy_demo_utils/ivy_scene/no_sim/__init__.py
ivy_demo_utils/ivy_scene/no_sim/obj_bbx_0.npy
ivy_demo_utils/ivy_scene/no_sim/obj_bbx_1.npy
ivy_demo_utils/ivy_scene/no_sim/obj_bbx_10.npy
ivy_demo_utils/ivy_scene/no_sim/obj_bbx_2.npy
ivy_demo_utils/ivy_scene/no_sim/obj_bbx_3.npy
ivy_demo_utils/ivy_scene/no_sim/obj_bbx_4.npy
ivy_demo_utils/ivy_scene/no_sim/obj_bbx_5.npy
ivy_demo_utils/ivy_scene/no_sim/obj_bbx_6.npy
ivy_demo_utils/ivy_scene/no_sim/obj_bbx_7.npy
ivy_demo_utils/ivy_scene/no_sim/obj_bbx_8.npy
ivy_demo_utils/ivy_scene/no_sim/obj_bbx_9.npy
ivy_demo_utils/ivy_scene/no_sim/obj_inv_ext_mat_0.npy
ivy_demo_utils/ivy_scene/no_sim/obj_inv_ext_mat_1.npy
ivy_demo_utils/ivy_scene/no_sim/obj_inv_ext_mat_10.npy
ivy_demo_utils/ivy_scene/no_sim/obj_inv_ext_mat_2.npy
ivy_demo_utils/ivy_scene/no_sim/obj_inv_ext_mat_3.npy
ivy_demo_utils/ivy_scene/no_sim/obj_inv_ext_mat_4.npy
ivy_demo_utils/ivy_scene/no_sim/obj_inv_ext_mat_5.npy
ivy_demo_utils/ivy_scene/no_sim/obj_inv_ext_mat_6.npy
ivy_demo_utils/ivy_scene/no_sim/obj_inv_ext_mat_7.npy
ivy_demo_utils/ivy_scene/no_sim/obj_inv_ext_mat_8.npy
ivy_demo_utils/ivy_scene/no_sim/obj_inv_ext_mat_9.npy
ivy_demo_utils-1.1.9.dist-info/LICENCE
ivy_demo_utils-1.1.9.dist-info/METADATA
ivy_demo_utils-1.1.9.dist-info/WHEEL
ivy_demo_utils-1.1.9.dist-info/top_level.txt
ivy_demo_utils-1.1.9.dist-info/RECORD
