Metadata-Version: 2.1
Name: ivy-demo-utils
Version: 1.1.9
Summary: Ivy Demo Utils provides a set of utilities for creating visual demos for Ivy libraries.
Home-page: UNKNOWN
Author: Ivy Team
Author-email: ivydl.team@gmail.com
License: Apache 2.0
Platform: UNKNOWN
Classifier: License :: OSI Approved :: Apache Software License
License-File: LICENCE
Requires-Dist: open3d
